cdk_cloudformation_awscommunity_time_sleep/__init__.py
cdk_cloudformation_awscommunity_time_sleep/py.typed
cdk_cloudformation_awscommunity_time_sleep/_jsii/__init__.py
cdk_cloudformation_awscommunity_time_sleep/_jsii/awscommunity-time-sleep@1.9.0-alpha.7.jsii.tgz
cdk_cloudformation_awscommunity_time_sleep-1.9.0a7.dist-info/LICENSE
cdk_cloudformation_awscommunity_time_sleep-1.9.0a7.dist-info/METADATA
cdk_cloudformation_awscommunity_time_sleep-1.9.0a7.dist-info/WHEEL
cdk_cloudformation_awscommunity_time_sleep-1.9.0a7.dist-info/top_level.txt
cdk_cloudformation_awscommunity_time_sleep-1.9.0a7.dist-info/RECORD
